plquery/__init__.py
plquery/__main__.py
plquery-0.1.0.dist-info/METADATA
plquery-0.1.0.dist-info/WHEEL
plquery-0.1.0.dist-info/entry_points.txt
plquery-0.1.0.dist-info/licenses/LICENSE
plquery-0.1.0.dist-info/RECORD
