Metadata-Version: 2.4
Name: plquery
Version: 0.1.0
Summary: Query dataframes interactively
Project-URL: repository, https://github.com/pavelzw/plquery
Author-email: Pavel Zwerschke <pavelzw@gmail.com>
License: BSD 3-Clause License
License-File: LICENSE
Classifier: Programming Language :: Python :: 3
Classifier: Programming Language :: Python :: 3.13
Requires-Python: >=3.13
Requires-Dist: polars<2,>=1.26.0
Requires-Dist: textual<4,>=3.0.0
